[
  
  
    {
      "title"    : "页面没有找到",
      "url"      : "http://localhost:4000/404.html"
    } ,
  
  
  
    {
      "title"    : "我是谁 我在哪 我想说",
      "url"      : "http://localhost:4000/about/"
    } ,
  
  
  
    {
      "title"    : "博客分类",
      "url"      : "http://localhost:4000/categories/"
    } ,
  
  
  
  
  
    {
      "title"    : "友情链接",
      "url"      : "http://localhost:4000/links/"
    } ,
  
  
  
    {
      "title"    : "github 瞎折腾",
      "url"      : "http://localhost:4000/open-source/"
    } ,
  
  
  
  
  
    {
      "title"    : "Wiki",
      "url"      : "http://localhost:4000/wiki/"
    } ,
  
  
  
  
  
  
  
  
  
  
  
  

  
    {
      "title"    : "浏览器 or 计算机系列文章",
      "category" : "计算机",
      "url"      : "http://localhost:4000/2019/07/04/computer/"
    } ,
  
    {
      "title"    : "flutter 入门学习",
      "category" : "flutter",
      "url"      : "http://localhost:4000/2019/07/04/flutter/"
    } ,
  
    {
      "title"    : "go 入门学习",
      "category" : "go",
      "url"      : "http://localhost:4000/2019/07/04/go/"
    } ,
  
    {
      "title"    : "Hello World",
      "category" : "生活",
      "url"      : "http://localhost:4000/2019/07/04/hello-world/"
    } ,
  
    {
      "title"    : "nuxt 入门学习",
      "category" : "nuxt",
      "url"      : "http://localhost:4000/2019/07/04/nuxt/"
    } ,
  
    {
      "title"    : "react 项目学习",
      "category" : "react",
      "url"      : "http://localhost:4000/2019/07/04/react/"
    } ,
  
    {
      "title"    : "vue 系列小实例",
      "category" : "vue",
      "url"      : "http://localhost:4000/2019/07/04/vue-practice/"
    } ,
  
    {
      "title"    : "vue 系列文章推荐",
      "category" : "vue",
      "url"      : "http://localhost:4000/2019/07/04/vue-recommend/"
    } ,
  
    {
      "title"    : "前端规范",
      "category" : "前端面试",
      "url"      : "http://localhost:4000/2019/07/05/css-standard/"
    } ,
  
    {
      "title"    : "前端面试系列文章",
      "category" : "前端面试",
      "url"      : "http://localhost:4000/2019/07/05/interview/"
    } ,
  
    {
      "title"    : "JavaScript 库 + UI插件推荐 + 周边技术",
      "category" : "web",
      "url"      : "http://localhost:4000/2019/07/05/web/"
    } ,
  
    {
      "title"    : "解决工作bug或者需求系列文章",
      "category" : "解决问题",
      "url"      : "http://localhost:4000/2019/07/05/work/"
    } ,
  
    {
      "title"    : "算不算算法的算法",
      "category" : "算法",
      "url"      : "http://localhost:4000/2019/07/08/algorithm001/"
    } ,
  
    {
      "title"    : "JavaScript 知识点概念",
      "category" : "",
      "url"      : "http://localhost:4000/2019/07/08/javascript/"
    } ,
  
    {
      "title"    : "前端项目的搭建",
      "category" : "项目搭建",
      "url"      : "http://localhost:4000/2019/07/08/vue-cli/"
    } ,
  
    {
      "title"    : "前端技术文章推荐",
      "category" : "web",
      "url"      : "http://localhost:4000/2019/07/09/web-recommend/"
    } ,
  
    {
      "title"    : "Eclipse",
      "category" : "Eclipse",
      "url"      : "http://localhost:4000/wiki/eclipse/"
    } ,
  
    {
      "title"    : "Git",
      "category" : "Git",
      "url"      : "http://localhost:4000/wiki/git/"
    } ,
  
    {
      "title"    : "Linux/Unix",
      "category" : "Linux",
      "url"      : "http://localhost:4000/wiki/linux/"
    } ,
  
    {
      "title"    : "Mac OS X",
      "category" : "Mac",
      "url"      : "http://localhost:4000/wiki/mac/"
    } ,
  
    {
      "title"    : "Markdown",
      "category" : "Markdown",
      "url"      : "http://localhost:4000/wiki/markdown/"
    } ,
  
    {
      "title"    : "OneNote",
      "category" : "Tools",
      "url"      : "http://localhost:4000/wiki/onenote/"
    } ,
  
    {
      "title"    : "PHP",
      "category" : "php",
      "url"      : "http://localhost:4000/wiki/php/"
    } ,
  
    {
      "title"    : "Python",
      "category" : "Python",
      "url"      : "http://localhost:4000/wiki/python/"
    } ,
  
    {
      "title"    : "Vim",
      "category" : "Vim",
      "url"      : "http://localhost:4000/wiki/vim/"
    } 
  
]
